funnyiest/__init__.py
funnyiest/text.py
funnyiest-0.2.dist-info/METADATA
funnyiest-0.2.dist-info/WHEEL
funnyiest-0.2.dist-info/top_level.txt
funnyiest-0.2.dist-info/RECORD
